dk64_lib/__init__.py
dk64_lib/file_io.py
dk64_lib/rom.py
dk64_lib/components/__init__.py
dk64_lib/components/triangle.py
dk64_lib/components/vertex.py
dk64_lib/constants/__init__.py
dk64_lib/constants/kiosk_sprites.py
dk64_lib/constants/maps.py
dk64_lib/constants/release_sprites.py
dk64_lib/data_types/__init__.py
dk64_lib/data_types/base.py
dk64_lib/data_types/cutscene.py
dk64_lib/data_types/geometry.py
dk64_lib/data_types/text.py
dk64_lib/data_types/texture.py
dk64_lib/f3dex2/__init__.py
dk64_lib/f3dex2/commands.py
dk64_lib/f3dex2/display_list.py
dk64_lib-0.1.0.dist-info/LICENSE
dk64_lib-0.1.0.dist-info/METADATA
dk64_lib-0.1.0.dist-info/WHEEL
dk64_lib-0.1.0.dist-info/top_level.txt
dk64_lib-0.1.0.dist-info/RECORD
