Metadata-Version: 2.1
Name: dk64-lib
Version: 0.1.0
License: GNU GENERAL PUBLIC LICENSE
Requires-Python: >=3.10
License-File: LICENSE
